aiodatalite/__init__.py
aiodatalite/commons.py
aiodatalite/constraints.py
aiodatalite/datalite_decorator.py
aiodatalite/fetch.py
aiodatalite/mass_actions.py
aiodatalite/migrations.py
aiodatalite/typed.py
aiodatalite-1.0.4.dist-info/LICENSE
aiodatalite-1.0.4.dist-info/METADATA
aiodatalite-1.0.4.dist-info/WHEEL
aiodatalite-1.0.4.dist-info/RECORD
