Metadata-Version: 2.3
Name: aiodatalite
Version: 1.0.4
Summary: A simple Python library to bind dataclasses with databases. Now asynchronous!
Author: hhh
Author-email: shshshsh@horsefucker.org
Requires-Python: >=3.9
Classifier: Programming Language :: Python :: 3
Classifier: Programming Language :: Python :: 3.9
Classifier: Programming Language :: Python :: 3.10
Classifier: Programming Language :: Python :: 3.11
Classifier: Programming Language :: Python :: 3.12
Classifier: Programming Language :: Python :: 3.13
Requires-Dist: aiosqlite (>=0.20.0,<0.21.0)
Project-URL: Documentation, https://aiodatalite.readthedocs.io
Project-URL: Repository, https://github.com/kotikotprojects/aiodatalite
